MANIFEST.in
README.md
requirements.txt
setup.py
bam2html/__init__.py
bam2html.egg-info/PKG-INFO
bam2html.egg-info/SOURCES.txt
bam2html.egg-info/dependency_links.txt
bam2html.egg-info/entry_points.txt
bam2html.egg-info/requires.txt
bam2html.egg-info/top_level.txt
bam2html/bin/__init__.py
bam2html/bin/main.py
bam2html/core/__init__.py
bam2html/util/__init__.py
bam2html/util/template.py
bam2html/version/version.json