Metadata-Version: 2.1
Name: bam2html
Version: 1.0.4
Summary: View Bam in Highlighted HTML
Home-page: https://github.com/suqingdong/bam2html
Author: suqingdong
Author-email: 1078595229@qq.com
License: BSD License
Project-URL: Documentation, https://bam2html.readthedocs.io
Project-URL: Tracker, https://github.com/suqingdong/bam2html/issues
Platform: UNKNOWN
Classifier: Development Status :: 5 - Production/Stable
Classifier: Operating System :: OS Independent
Classifier: Intended Audience :: Developers
Classifier: License :: OSI Approved :: BSD License
Classifier: Programming Language :: Python
Classifier: Programming Language :: Python :: 2
Classifier: Programming Language :: Python :: 2.7
Classifier: Programming Language :: Python :: 3
Classifier: Programming Language :: Python :: 3.6
Classifier: Topic :: Software Development :: Libraries
